restful_client_lite/__init__.py
restful_client_lite/__version__.py
restful_client_lite/clients.py
restful_client_lite/contrib/__init__.py
restful_client_lite/contrib/aliyun.py
restful_client_lite/contrib/wangduoyun.py
restful_client_lite-0.0.5.dist-info/LICENSE
restful_client_lite-0.0.5.dist-info/METADATA
restful_client_lite-0.0.5.dist-info/WHEEL
restful_client_lite-0.0.5.dist-info/top_level.txt
restful_client_lite-0.0.5.dist-info/RECORD
